pycocotools/__init__.py
pycocotools/_mask.cp39-win_amd64.pyd
pycocotools/coco.py
pycocotools/cocoeval.py
pycocotools/mask.py
pycocotools_og-2.0.6.dist-info/METADATA
pycocotools_og-2.0.6.dist-info/WHEEL
pycocotools_og-2.0.6.dist-info/top_level.txt
pycocotools_og-2.0.6.dist-info/RECORD
